{
    "Al Ahli M.": {
        "corners": {},
        "goals": {
            "over_1_5": "73%",
            "over_2_5": "47%",
            "over_3_5": "20%",
            "bts": "47%"
        },
        "position": {
            "posicion": 7,
            "partidos": 15,
            "ganados": 5,
            "empatados": 3,
            "perdidos": 7,
            "goles_favor": 20,
            "goles_contra": 21,
            "diferencia": -1,
            "puntos": 18
        }
    },
    "Al-Muharraq": {
        "corners": {},
        "goals": {
            "over_1_5": "73%",
            "over_2_5": "40%",
            "over_3_5": "13%",
            "bts": "20%"
        },
        "position": {
            "posicion": 1,
            "partidos": 15,
            "ganados": 11,
            "empatados": 3,
            "perdidos": 1,
            "goles_favor": 33,
            "goles_contra": 4,
            "diferencia": 29,
            "puntos": 36
        }
    },
    "Sitra": {
        "corners": {},
        "goals": {
            "over_1_5": "67%",
            "over_2_5": "47%",
            "over_3_5": "27%",
            "bts": "47%"
        },
        "position": {
            "posicion": 10,
            "partidos": 15,
            "ganados": 3,
            "empatados": 6,
            "perdidos": 6,
            "goles_favor": 12,
            "goles_contra": 22,
            "diferencia": -10,
            "puntos": 15
        }
    },
    "Budaiya": {
        "corners": {},
        "goals": {
            "over_1_5": "80%",
            "over_2_5": "60%",
            "over_3_5": "27%",
            "bts": "60%"
        },
        "position": {
            "posicion": 8,
            "partidos": 15,
            "ganados": 5,
            "empatados": 3,
            "perdidos": 7,
            "goles_favor": 20,
            "goles_contra": 22,
            "diferencia": -2,
            "puntos": 18
        }
    },
    "Bahrain SC": {
        "corners": {},
        "goals": {
            "over_1_5": "80%",
            "over_2_5": "60%",
            "over_3_5": "40%",
            "bts": "33%"
        },
        "position": {
            "posicion": 12,
            "partidos": 15,
            "ganados": 2,
            "empatados": 1,
            "perdidos": 12,
            "goles_favor": 10,
            "goles_contra": 37,
            "diferencia": -27,
            "puntos": 7
        }
    },
    "Al Shabbab": {
        "corners": {},
        "goals": {
            "over_1_5": "60%",
            "over_2_5": "27%",
            "over_3_5": "13%",
            "bts": "20%"
        },
        "position": {
            "posicion": 11,
            "partidos": 15,
            "ganados": 2,
            "empatados": 3,
            "perdidos": 10,
            "goles_favor": 5,
            "goles_contra": 24,
            "diferencia": -19,
            "puntos": 9
        }
    },
    "Malkiya": {
        "corners": {},
        "goals": {
            "over_1_5": "53%",
            "over_2_5": "27%",
            "over_3_5": "13%",
            "bts": "40%"
        },
        "position": {
            "posicion": 4,
            "partidos": 15,
            "ganados": 6,
            "empatados": 5,
            "perdidos": 4,
            "goles_favor": 15,
            "goles_contra": 12,
            "diferencia": 3,
            "puntos": 23
        }
    },
    "Al-Najma": {
        "corners": {},
        "goals": {
            "over_1_5": "80%",
            "over_2_5": "40%",
            "over_3_5": "13%",
            "bts": "40%"
        },
        "position": {
            "posicion": 9,
            "partidos": 15,
            "ganados": 4,
            "empatados": 3,
            "perdidos": 8,
            "goles_favor": 13,
            "goles_contra": 23,
            "diferencia": -10,
            "puntos": 15
        }
    },
    "AAli FC": {
        "corners": {},
        "goals": {
            "over_1_5": "53%",
            "over_2_5": "33%",
            "over_3_5": "7%",
            "bts": "33%"
        },
        "position": {
            "posicion": 6,
            "partidos": 15,
            "ganados": 5,
            "empatados": 4,
            "perdidos": 6,
            "goles_favor": 13,
            "goles_contra": 15,
            "diferencia": -2,
            "puntos": 19
        }
    },
    "League average": {
        "corners": {},
        "goals": {
            "over_1_5": "45.6%",
            "over_2_5": "20.0%",
            "over_3_5": "8.9%",
            "bts": "34.4%"
        },
        "position": {}
    },
    "Al-Hidd": {
        "corners": {},
        "goals": {
            "over_1_5": "80%",
            "over_2_5": "67%",
            "over_3_5": "33%",
            "bts": "60%"
        },
        "position": {
            "posicion": 5,
            "partidos": 15,
            "ganados": 5,
            "empatados": 6,
            "perdidos": 4,
            "goles_favor": 24,
            "goles_contra": 18,
            "diferencia": 6,
            "puntos": 21
        }
    },
    "Khalidiya": {
        "corners": {},
        "goals": {
            "over_1_5": "60%",
            "over_2_5": "53%",
            "over_3_5": "20%",
            "bts": "33%"
        },
        "position": {
            "posicion": 2,
            "partidos": 15,
            "ganados": 12,
            "empatados": 0,
            "perdidos": 3,
            "goles_favor": 26,
            "goles_contra": 9,
            "diferencia": 17,
            "puntos": 36
        }
    },
    "Al Riffa": {
        "corners": {},
        "goals": {
            "over_1_5": "80%",
            "over_2_5": "47%",
            "over_3_5": "13%",
            "bts": "33%"
        },
        "position": {
            "posicion": 3,
            "partidos": 15,
            "ganados": 10,
            "empatados": 3,
            "perdidos": 2,
            "goles_favor": 26,
            "goles_contra": 10,
            "diferencia": 16,
            "puntos": 33
        }
    },
    "_metadata": {
        "fecha_actualizacion": "2026-03-12T13:50:49.854280",
        "liga": "bahrain"
    }
}